odaexperiments/__init__.py
odaexperiments/app.py
odaexperiments/cli.py
odaexperiments/compose.py
odaexperiments/run.py
odaexperiments/worker.py
odaexperiments/workflow.py
odaexperiments/static/favicon.png
odaexperiments/static/css/style.css
odaexperiments/static/img/rdf.svg
odaexperiments/templates/add-form.html
odaexperiments/templates/dashboard.html
odaexperiments/templates/data.html
odaexperiments/templates/facts-about-integral.html
odaexperiments/templates/features.html
odaexperiments/templates/layout.html
odaexperiments/templates/objects.html
odaexperiments/templates/papers.html
odaexperiments/templates/viewdata.html
odaexperiments/templates/workflow.html
odaexperiments/templates/workflows.html
oda_experiments-0.1.0.dist-info/COPYING
oda_experiments-0.1.0.dist-info/METADATA
oda_experiments-0.1.0.dist-info/WHEEL
oda_experiments-0.1.0.dist-info/entry_points.txt
oda_experiments-0.1.0.dist-info/top_level.txt
oda_experiments-0.1.0.dist-info/RECORD
